README.md
setup.cfg
setup.py
NetBone/Backbone.py
NetBone/Compare.py
NetBone/Filters.py
NetBone/Measures.py
NetBone/Visualize.py
NetBone/__init__.py
NetBone.egg-info/PKG-INFO
NetBone.egg-info/SOURCES.txt
NetBone.egg-info/dependency_links.txt
NetBone.egg-info/requires.txt
NetBone.egg-info/top_level.txt
NetBone/Statistical/__init__.py
NetBone/Statistical/disparity.py
NetBone/Statistical/global_threshold.py
NetBone/Statistical/lans.py
NetBone/Statistical/marginal_likelihood.py
NetBone/Statistical/noise_corrected.py
NetBone/Statistical/maxent_graph/MaxentGraph.py
NetBone/Statistical/maxent_graph/__init__.py
NetBone/Statistical/maxent_graph/ecm.py
NetBone/Statistical/maxent_graph/ecm_main.py
NetBone/Statistical/maxent_graph/util.py
NetBone/Structural/__init__.py
NetBone/Structural/doubly_stochastic.py
NetBone/Structural/h_backbone.py
NetBone/Structural/high_salience_skeleton.py
NetBone/Structural/maximum_spanning_tree.py
NetBone/Structural/metric_distance_backbone.py
NetBone/Structural/modulairy_backbone.py
NetBone/Structural/ultrametric_distance_backbone.py
NetBone/Structural/distanceclosure/__init__.py
NetBone/Structural/distanceclosure/backbone.py
NetBone/Structural/distanceclosure/closure.py
NetBone/Structural/distanceclosure/dijkstra.py
NetBone/Structural/distanceclosure/distance.py
NetBone/Structural/distanceclosure/utils.py
NetBone/Structural/distanceclosure/cython/__init__.py
NetBone/Utils/__init__.py
NetBone/Utils/narrate.py
NetBone/Utils/utils.py