Metadata-Version: 2.1
Name: NetBone
Version: 0.17
Summary: A python package for extracting network backbones from simple weighted networks
Home-page: https://gitlab.liris.cnrs.fr/coregraphie/netbone
Author: Ali Yassin
Author-email: aliyassin4@hotmail.com
License: MIT
Keywords: backbone network
